irritable/__init__.py
irritable/irritable.py
irritable-0.1.0.dist-info/DESCRIPTION.rst
irritable-0.1.0.dist-info/METADATA
irritable-0.1.0.dist-info/RECORD
irritable-0.1.0.dist-info/WHEEL
irritable-0.1.0.dist-info/metadata.json
irritable-0.1.0.dist-info/top_level.txt
