Metadata-Version: 2.0
Name: irritable
Version: 0.1.0
Summary: Irritable implements broken iterators called irritables
Home-page: https://github.com/timb07/irritable
Author: Tim Bell
Author-email: timothybell@gmail.com
License: BSD license
Keywords: irritable
Platform: UNKNOWN
Classifier: Development Status :: 2 - Pre-Alpha
Classifier: Intended Audience :: Developers
Classifier: License :: OSI Approved :: BSD License
Classifier: Natural Language :: English
Classifier: Programming Language :: Python :: 3
Classifier: Programming Language :: Python :: 3.5
Classifier: Programming Language :: Python :: 3.6
